{"MLErx7gTtp1xJGM3M3whgA==":"com-fundo.png","yeDtN+jqoI8NkcHy9Xqo6Q==":"com-fundo-1.png","MK7cX07TUffBUDHxWKAeGQ==":"sem-fundo.png","CRderviXRM/AQfD8ckVCEA==":"sem-fundo1.png","jLonI37sf6hLgaFP6t02cA==":"residencial.jpg","E2o7jligzlVCIkE8kt19ag==":"photo-1-2025-04-03-16-34.jpg","e/pCoO8ai3tWqwvILDRRmQ==":"rolo.png","YGg3sDfLj8a1PjX/y1kdSQ==":"rolo-1.png","QOFlD3LgcU/xncDOfo22Hg==":"472430387-902301468742306-6955022787072005212-n.jpg","oj+VtgjCsaIMRqRQNBd+ew==":"sanesul.jpg","xRrKSWzulx3gepIQM0YUYw==":"colgio-grupo-mackenzie-alecrim-dourado-logo.jpg","9I8MPOTTHaw57CGXWD6VXA==":"novo-colorido-400x400.jpg","K+DdKH8IgRHku13tPJW+mw==":"305310426-457491416394864-1406647319019650741-n.jpg","DNz6TFZxhv851H4jY8O3/A==":"logo17228700716j20.png","y6ySXZR0TeZp49aj3Xckbg==":"channels4-profile.jpg","6/n0ZkYxsc/55KfjEU1Y7g==":"images-1.jpg","pVWWvwuoKmudlKbz+8vfHQ==":"central.png","qLDodkDCLOB+wPN0J4lClw==":"business-logo.png","R2eG1y0GFzrcwZbuakGPcQ==":"28f61e-f2f73607608a497fbc0c129bf798ffc3mv2.jpg","ySR4FNndIiHvCIVPdzFmzw==":"img-318.jpg","zvxg403gu0fcJIVUqcpBZQ==":"2019-3.jpg","q0BbHfiJ6VUjc6EymMoQQA==":"balde-since.png-160x160.png","1XHZgDwdah35dAsX3lcLUQ==":"balde-since.png-1-160x160.png","Pu3imClxvs0qxfMjB7P7iA==":"balde-since.png-2-160x160.png","vKX/WyAOefsd6gthsn57AQ==":"balde-since.png-3-160x160.png","54oB/J+vaiUikmZt2P8p9A==":"photo-5-2025-04-03-16-34.jpg","E0GpyWMv9g1MPrFfgxrnXQ==":"photo-6-2025-04-03-16-34.jpg","kF+D0p+hsy5bsupHtA5BVg==":"photo-2-2025-04-12-09-42-29.jpg-960x539.jpg","90TlS9O6hYUIDw52Nqltjg==":"photo-13-2025-04-12-09-42-29.jpg-828x850.jpg","KaEX8ixcz+bFJ74KdnalGw==":"photo-2025-04-12-09-55-17.jpg-828x811.jpg","POyG59RYgXfKSU20yDHGNA==":"eta.jpg-1300x730.jpg","bhl24UBfjfKniMqBAzPO7Q==":"eb.jpg-768x960.jpg","JNpisgJ6IsSQh5os7+sINw==":"rancho-terra1.jpg-828x306.jpg","zxiuwAUUMOw0vWpZVM6wXA==":"rancho-terra.jpg-828x828.jpg","Nprd1Cp1autP5v7VqCG5nw==":"eb.jpg-768x960.jpeg","xzBBUKi5q/sErq4byWQ/vA==":"eb1.jpg-1-400x228.jpg","/yW1kuUJyQQbqorYnjN3pQ==":"photo-4-2025-04-12-09-42-29.jpg-1-539x302.jpg","H3RygKu6Vr0aeDA7QBwYcg==":"photo-3-2025-04-12-09-42-29.jpg-1-539x302.jpg","KVdVcEPxyI2WOA57GLlB9A==":"photo-15-2025-04-12-09-42-29.jpg-1-828x743.jpg","XqStexa3ucYeWEdbgE9USg==":"background1.jpg","pj/JICBqBJUKdKhgE3RvhA==":"photo-1-2025-04-12-09-42-28.jpg-1-1273x1266.jpg","cUV6J+0WITdsIYWcqfUCoA==":"photo-5-2025-04-12-09-42-29.jpg-1-1032x774.jpg","QtaQP5rgnIzJ09rUJRW3zw==":"photo-6-2025-04-12-09-42-29.jpg-1-774x1032.jpg","IJHTKLIIgvXyNmFMzq7pEA==":"photo-7-2025-04-12-09-42-29.jpg-1-1032x774.jpg","44+YVoHu+Rm7T7lK6S36bg==":"photo-16-2025-04-12-09-42-29.jpg-1-828x815.jpg","9t7iJkv1Kbw+QNFCaoioig==":"10.jpg","CimcYMHYzphkrvKnUQ7kDA==":"balde-since.png-4-160x160.png","jIsOdVgkq/Vck2DsW27pyg==":"balde-since.png-5-160x160.png","4HuTDnmrwgA5HzimCzDILA==":"photo-2-2025-04-03-16.jpg","cF8Y1RQWxeVzmbzpA6yQzw==":"photo-3-2025-04-03-16.jpg","TjyqgAA2QaNMBFm6e2WGYw==":"photo-8-2025-04-03-16.jpg","PXVaXnl1pTDVbrN8BYA2Dw==":"background3.jpg","D1es1ziwlNO1SU7NtZ02gA==":"6.jpg","3dgAb8UPwh/o8QJ/kgnaxw==":"shop1.jpg","9PN0ZNPNoLhLhe1Hx7Dk1A==":"shop3.jpg","X2njN3VMAulfBX9K/2cyjQ==":"shop2.jpg","porvOfE5hpWkKLPm6fIDCA==":"shop4.jpg","XB/oyi75ZpcdBQ6O6M6+Bg==":"shop6.jpg","BMC2UlTY6RRjhUmUbgpiJQ==":"shop5.jpg","3oTS/iISou90UR4ZPEIupg==":"eb.jpg-1-768x960.jpeg","hMtAfRMbSC4WX3Obyoj22Q==":"eb.jpg-2-768x960.jpeg","3233hwONUVveEt4bXDgcog==":"photo-12-2025-04-12-09-42-29.jpg-828x800.jpg","9Gkwa2BRUi3IzywSPSeN0w==":"photo-12-2025-04-12-09-42-29.jpg-828x800.jpeg"}